jongten/__init__.py
jongten/__main__.py
jongten/jongten.py
jongten/question.py
jongten/questions.py
jongten/util.py
jongten-0.1.8.dist-info/entry_points.txt
jongten-0.1.8.dist-info/WHEEL
jongten-0.1.8.dist-info/METADATA
jongten-0.1.8.dist-info/RECORD
