Metadata-Version: 2.1
Name: jongten
Version: 0.1.8
Summary: CLI trainer for calculating riichi-mahjong points
Home-page: http://github.com/odmishien/jongten
License: MIT
Keywords: mahjong,CLI
Author: odmishien
Author-email: tmtm.yagi.007@gmail.com
Requires-Python: >=3.9,<4.0
Classifier: License :: OSI Approved :: MIT License
Classifier: Programming Language :: Python :: 3
Classifier: Programming Language :: Python :: 3.9
Requires-Dist: mahjong (>=1.1.11,<2.0.0)
Project-URL: Repository, http://github.com/odmishien/jongten
